{
  "entity_name": "chainsaw-fgunsfcases-juggle-ru",
  "ad_apps": [
  	{
      "order": 1,
      "package_id": "com.happylion.chainsaw",
      "icon": "chainsaw_icon.png",
      "name": "Бензопила!!!"
    },
    {
      "order": 2,
      "package_id": "com.lightside.fgunsfcases",
      "icon": "4guns4cases_icon.png",
      "name": "Ultimate Case Quiz"
    },
    {
      "order": 3,
      "package_id": "com.twodtwob.juggleball",
      "icon": "juggledot_icon.png",
      "name": "Juggle Dot"
    }
  ]
}